waclient/__init__.py
waclient/client.py
waclient/exceptions.py
waclient/media.py
waclient/messages.py
waclient/templates.py
waclient/utils.py
waclient/webhooks.py
waclient-0.1.9.dist-info/licenses/LICENSE
waclient-0.1.9.dist-info/METADATA
waclient-0.1.9.dist-info/WHEEL
waclient-0.1.9.dist-info/top_level.txt
waclient-0.1.9.dist-info/RECORD
