Metadata-Version: 2.4
Name: waclient
Version: 0.1.9
Summary: Simplified Python SDK for WhatsApp Business Cloud API
Author: Surenthar
License-Expression: MIT
Project-URL: Bug Reports, https://github.com/surenthars/waclient/issues
Project-URL: Source, https://github.com/surenthars/waclient
Project-URL: Documentation, https://github.com/surenthars/waclient#readme
Keywords: whatsapp,business,api,cloud,meta,facebook,messaging
Classifier: Development Status :: 3 - Alpha
Classifier: Intended Audience :: Developers
Classifier: Topic :: Communications :: Chat
Classifier: Programming Language :: Python :: 3
Classifier: Programming Language :: Python :: 3.7
Classifier: Programming Language :: Python :: 3.8
Classifier: Programming Language :: Python :: 3.9
Classifier: Programming Language :: Python :: 3.10
Classifier: Programming Language :: Python :: 3.11
Classifier: Programming Language :: Python :: 3.12
Requires-Python: >=3.8
License-File: LICENSE
Requires-Dist: requests>=2.25.0
Provides-Extra: dev
Requires-Dist: pytest>=6.0; extra == "dev"
Requires-Dist: pytest-cov>=2.0; extra == "dev"
Requires-Dist: black>=21.0; extra == "dev"
Requires-Dist: flake8>=3.9; extra == "dev"
Dynamic: license-file
